pyi4thrift/__init__.py
pyi4thrift/__main__.py
pyi4thrift/__version__.py
pyi4thrift/convert.py
pyi4thrift/exceptions.py
pyi4thrift/main.py
pyi4thrift/peg.py
pyi4thrift/py.typed
pyi4thrift-2.1.0.dist-info/METADATA
pyi4thrift-2.1.0.dist-info/WHEEL
pyi4thrift-2.1.0.dist-info/entry_points.txt
pyi4thrift-2.1.0.dist-info/licenses/LICENSE
pyi4thrift-2.1.0.dist-info/RECORD
