Metadata-Version: 2.4
Name: pyi4thrift
Version: 2.1.0
Summary: convert thrift to pyi
Project-URL: Homepage, https://github.com/sagewe/pyi4thrift
Project-URL: Bug Tracker, https://github.com/sagewe/pyi4thrift/issues
Author-email: yanweizhi <yanweizhi@bytedance.com>
Maintainer-email: sagewe <sagewe@fastmail.com>
License: MIT License
License-File: LICENSE
Classifier: Intended Audience :: Developers
Classifier: Programming Language :: Python :: 3
Classifier: Programming Language :: Python :: 3.9
Classifier: Programming Language :: Python :: 3.10
Classifier: Programming Language :: Python :: 3.11
Requires-Python: >=3.9
Requires-Dist: lark<2.0.0,>=1.1.9
Requires-Dist: thriftpy2<1.0.0,>=0.4.2
Requires-Dist: yapf<1.0.0,>=0.22.0
Provides-Extra: dev
Requires-Dist: flake8<7.0.0,>=6.1.0; extra == 'dev'
Requires-Dist: mypy<2.0.0,>=1.7.0; extra == 'dev'
Requires-Dist: pytest-cov<5.0.0,>=4.1.0; extra == 'dev'
Requires-Dist: pytest<8.0.0,>=7.4.0; extra == 'dev'
Requires-Dist: tox<5.0.0,>=4.11.0; extra == 'dev'
